svglab/__init__.py
svglab/attrparse/__init__.py
svglab/attrparse/angle.py
svglab/attrparse/color.py
svglab/attrparse/grammars/angle.lark
svglab/attrparse/grammars/length.lark
svglab/attrparse/grammars/path_data.lark
svglab/attrparse/grammars/point.lark
svglab/attrparse/grammars/points.lark
svglab/attrparse/grammars/transform.lark
svglab/attrparse/iri.py
svglab/attrparse/length.py
svglab/attrparse/parse.py
svglab/attrparse/path_data.py
svglab/attrparse/point.py
svglab/attrparse/points.py
svglab/attrparse/transform.py
svglab/attrs/__init__.py
svglab/attrs/attrdefs.py
svglab/attrs/attrgroups.py
svglab/attrs/names.py
svglab/attrs/typedefs.py
svglab/constants.py
svglab/elements/__init__.py
svglab/elements/elements.py
svglab/elements/names.py
svglab/elements/traits.py
svglab/entities.py
svglab/errors.py
svglab/graphics.py
svglab/mixins.py
svglab/models.py
svglab/parse.py
svglab/protocols.py
svglab/py.typed
svglab/serialize.py
svglab/units.py
svglab/utils/__init__.py
svglab/utils/bsutils.py
svglab/utils/iterutils.py
svglab/utils/mathutils.py
svglab/utils/miscutils.py
svglab/utiltypes.py
svglab-0.12.0.dist-info/LICENSE
svglab-0.12.0.dist-info/METADATA
svglab-0.12.0.dist-info/WHEEL
svglab-0.12.0.dist-info/RECORD
