Metadata-Version: 2.3
Name: svglab
Version: 0.12.0
Summary: A manipulation and optimization library for Scalable Vector Graphics
License: MIT
Keywords: svg,svg manipulation,image processing,vector graphics,image optimization,affine transformation
Author: Tomáš Režňák
Author-email: tomas.reznak@volny.cz
Requires-Python: >=3.10,<4.0
Classifier: Framework :: Pydantic :: 2
Classifier: Intended Audience :: Developers
Classifier: License :: OSI Approved :: MIT License
Classifier: Operating System :: OS Independent
Classifier: Programming Language :: Python :: 3
Classifier: Programming Language :: Python :: 3.10
Classifier: Programming Language :: Python :: 3.11
Classifier: Programming Language :: Python :: 3.12
Classifier: Programming Language :: Python :: 3.13
Classifier: Topic :: Multimedia :: Graphics
Classifier: Topic :: Multimedia :: Graphics :: Editors :: Vector-Based
Classifier: Topic :: Scientific/Engineering :: Image Processing
Classifier: Topic :: Text Processing :: Markup :: XML
Classifier: Typing :: Typed
Requires-Dist: affine (>=3.0b1,<4.0)
Requires-Dist: beautifulsoup4 (>=4.12.3,<5.0.0)
Requires-Dist: bidict (>=0.23.1,<0.24.0)
Requires-Dist: html5lib (>=1.1,<2.0)
Requires-Dist: lark (>=1.2.2,<2.0.0)
Requires-Dist: lxml (>=5.3.0,<6.0.0)
Requires-Dist: more-itertools (>=10.6.0,<11.0.0)
Requires-Dist: numpy (>=1.26.4,<3.0.0)
Requires-Dist: pillow (>=11.1.0,<12.0.0)
Requires-Dist: pydantic (>=2.0.0,<2.11.0)
Requires-Dist: pydantic-extra-types (>=2.10.1,<3.0.0)
Requires-Dist: resvg-py (>=0.1.6,<0.3.0)
Requires-Dist: rfc3986 (>=2.0.0,<3.0.0)
Requires-Dist: typing-extensions (>=4.12.2,<5.0.0)
Requires-Dist: uritools (>=5.0.0,<6.0.0)
Requires-Dist: useful-types (>=0.2.1,<0.3.0)
Project-URL: GitHub, https://github.com/reznakt/svglab
Project-URL: Issues, https://github.com/reznakt/svglab/issues
